iridis/__init__.py
iridis/color.py
iridis/color_prints.py
iridis/utils.py
iridis-0.2.3.dist-info/METADATA
iridis-0.2.3.dist-info/WHEEL
iridis-0.2.3.dist-info/licenses/LICENSE
iridis-0.2.3.dist-info/RECORD
