Metadata-Version: 2.3
Name: iridis
Version: 0.2.3
Summary: Useful methods for working in the terminal!
Author-email: Tobias Filgas <tobiasfilgas@gmail.com>
Maintainer-email: Tobias Filgas <tobiasfilgas@gmail.com>
License: MIT License
Requires-Python: >=3.8
